continuousflex/__init__.py
continuousflex/bibtex.py
continuousflex/conda.yaml
continuousflex/conda_noCuda.yaml
continuousflex/constants.py
continuousflex/protocols.conf
continuousflex/smog2.yaml
continuousflex/wizards.py
continuousflex/protocols/__init__.py
continuousflex/protocols/convert.py
continuousflex/protocols/data.py
continuousflex/protocols/protocol_align_pdbs.py
continuousflex/protocols/protocol_apply_volumeset_alignment.py
continuousflex/protocols/protocol_batch_cluster.py
continuousflex/protocols/protocol_batch_cluster_tomoflow.py
continuousflex/protocols/protocol_batch_cluster_vol.py
continuousflex/protocols/protocol_batch_pdb_cluster.py
continuousflex/protocols/protocol_ca2aa.py
continuousflex/protocols/protocol_deep_hemnma_infer.py
continuousflex/protocols/protocol_deep_hemnma_train.py
continuousflex/protocols/protocol_denoise_volumes.py
continuousflex/protocols/protocol_generate_topology.py
continuousflex/protocols/protocol_genesis.py
continuousflex/protocols/protocol_image_synthesize.py
continuousflex/protocols/protocol_mdspace.py
continuousflex/protocols/protocol_mdtomo.py
continuousflex/protocols/protocol_mw_restoration.py
continuousflex/protocols/protocol_nma.py
continuousflex/protocols/protocol_nma_alignment.py
continuousflex/protocols/protocol_nma_alignment_vol.py
continuousflex/protocols/protocol_nma_base.py
continuousflex/protocols/protocol_nma_choose.py
continuousflex/protocols/protocol_nma_dimred.py
continuousflex/protocols/protocol_nma_dimred_vol.py
continuousflex/protocols/protocol_pdb_dimred.py
continuousflex/protocols/protocol_pdb_synthesize.py
continuousflex/protocols/protocol_structure_mapping.py
continuousflex/protocols/protocol_subtomogram_averaging.py
continuousflex/protocols/protocol_subtomograms_classify.py
continuousflex/protocols/protocol_subtomograms_synthesize.py
continuousflex/protocols/protocol_tomoflow.py
continuousflex/protocols/protocol_tomoflow_dimred.py
continuousflex/protocols/protocol_tomoflow_refine_alignment.py
scipion_em_continuousflex-3.4.2.dist-info/LICENCE
scipion_em_continuousflex-3.4.2.dist-info/METADATA
scipion_em_continuousflex-3.4.2.dist-info/WHEEL
scipion_em_continuousflex-3.4.2.dist-info/entry_points.txt
scipion_em_continuousflex-3.4.2.dist-info/top_level.txt
scipion_em_continuousflex-3.4.2.dist-info/RECORD
