Metadata-Version: 2.1
Name: scipion-em-continuousflex
Version: 3.4.2
Summary: Plugin to use continuousflex protocols within the Scipion framework
Home-page: https://github.com/scipion-em/scipion-em-continuousflex
Author: Mohamad Harastani, Remi Vuillemot, Ilyes Hamitouche and Slavica Jonic
Author-email: slavica.jonic@upmc.fr
License: UNKNOWN
Project-URL: Bug Reports, https://github.com/scipion-em/scipion-em-continuousflex/issues
Project-URL: Source, https://github.com/scipion-em/scipion-em-continuousflex/
Keywords: cryo-em cryo-et image-processing continuous-conformational-variability
Platform: UNKNOWN
Classifier: Development Status :: 4 - Beta
Classifier: License :: OSI Approved :: GNU General Public License v3 (GPLv3)
Classifier: Programming Language :: Python :: 3
Requires-Dist: matplotlib
Requires-Dist: mrcfile
